sentry_yzj
