Metadata-Version: 2.1
Name: sentry-yzj
Version: 0.0.6
Summary: A Sentry extension which send errors stats to YunZhiJia
Home-page: https://github.com/slowwalkerlcr/sentry-yzj
Author: slowwalkerlcr
Author-email: slowwlakerlcr@163.com
License: MIT
Keywords: sentry yzj
Platform: UNKNOWN
Classifier: Programming Language :: Python :: 2.7
Classifier: License :: OSI Approved :: MIT License
